plyway/__init__.py
plyway/argument_parser.py
plyway/database/__init__.py
plyway/database/plyway_repo.py
plyway/exceptions.py
plyway/main.py
plyway/models.py
plyway/plyway_config.py
plyway-0.0.3.dist-info/METADATA
plyway-0.0.3.dist-info/WHEEL
plyway-0.0.3.dist-info/RECORD
